README.md
setup.cfg
setup.py
elisa_dnt/__init__.py
elisa_dnt/__main__.py
elisa_dnt/emoji.py
elisa_dnt/utils.py
elisa_dnt.egg-info/PKG-INFO
elisa_dnt.egg-info/SOURCES.txt
elisa_dnt.egg-info/dependency_links.txt
elisa_dnt.egg-info/requires.txt
elisa_dnt.egg-info/top_level.txt